kio/__init__.py
kio/__main__.py
kio/api.py
kio/cli.py
kio/time.py
stups_kio-0.1.26.dist-info/DESCRIPTION.rst
stups_kio-0.1.26.dist-info/METADATA
stups_kio-0.1.26.dist-info/RECORD
stups_kio-0.1.26.dist-info/WHEEL
stups_kio-0.1.26.dist-info/entry_points.txt
stups_kio-0.1.26.dist-info/metadata.json
stups_kio-0.1.26.dist-info/top_level.txt
