Metadata-Version: 2.0
Name: stups-kio
Version: 0.1.26
Summary: Simple command line utility to manage Kio applications
Home-page: https://github.com/zalando-stups/kio-cli
Author: Henning Jacobs
Author-email: henning.jacobs@zalando.de
License: Apache License 2.0
Keywords: stups kio application registry
Platform: UNKNOWN
Classifier: Development Status :: 4 - Beta
Classifier: Environment :: Console
Classifier: Intended Audience :: Developers
Classifier: Intended Audience :: System Administrators
Classifier: License :: OSI Approved :: Apache Software License
Classifier: Operating System :: POSIX :: Linux
Classifier: Programming Language :: Python
Classifier: Programming Language :: Python :: 3.6
Classifier: Programming Language :: Python :: 3.7
Classifier: Programming Language :: Python :: Implementation :: CPython
License-File: LICENSE
Requires-Dist: clickclick (>=0.9)
Requires-Dist: requests
Requires-Dist: stups-zign (>=1.0.10)
Requires-Dist: stups-cli-support (>=0.7)
